{
  "ticket_id": "TASK-SYS-034",
  "title": "Add agentskills.io standard frontmatter to all SKILL.md files",
  "description": "Update all SKILL.md files in .github/skills/ to conform to the agentskills.io open standard. Each SKILL.md must have YAML frontmatter with name (kebab-case), description (one-line), version (semver), author. Body must have Overview and Rules sections at minimum.",
  "type": "architecture",
  "priority": "medium",
  "stage": "DONE",
  "sdlc_flow": [
    "READY",
    "ARCHITECT",
    "DOCS",
    "VALIDATION",
    "DONE"
  ],
  "created_at": "2026-03-25T17:04:52.592809+00:00",
  "created_by": "TODO",
  "dependencies": [
    "TASK-SYS-025",
    "TASK-SYS-026"
  ],
  "blocked_by": [],
  "file_paths": [
    ".github/skills/a11y/SKILL.md",
    ".github/skills/agent-protocols/SKILL.md",
    ".github/skills/ai-safety/SKILL.md",
    ".github/skills/architecture/SKILL.md",
    ".github/skills/ci-cd/SKILL.md",
    ".github/skills/containerization/SKILL.md",
    ".github/skills/cto-playbook/SKILL.md",
    ".github/skills/design/SKILL.md",
    ".github/skills/implementation/SKILL.md",
    ".github/skills/orchestration/SKILL.md",
    ".github/skills/performance/SKILL.md",
    ".github/skills/planning/SKILL.md",
    ".github/skills/qa/SKILL.md",
    ".github/skills/sdlc/SKILL.md",
    ".github/skills/security/SKILL.md",
    ".github/skills/testing/SKILL.md"
  ],
  "acceptance_criteria": [
    "All SKILL.md files have name, description, version, author in frontmatter",
    "All SKILL.md files have Overview and Rules sections",
    "No skill content is lost during reformatting",
    "catalog.yml references remain valid"
  ],
  "rework_count": 0,
  "claimed_by": null,
  "machine_id": null,
  "operator": null,
  "lease_expiry": null,
  "lease_duration_minutes": 30,
  "history": [
    {
      "timestamp": "2026-03-25T17:04:52.592815+00:00",
      "event": "CREATED",
      "agent": "TODO",
      "machine_id": "system",
      "details": "Ticket created from TODO/tasks/EP3-skills-standard.md"
    },
    {
      "timestamp": "2026-03-26T10:46:19.413806+00:00",
      "event": "MOVED_TO_READY",
      "agent": "tickets.py",
      "machine_id": "system",
      "details": "Dependencies resolved, moved to READY"
    },
    {
      "timestamp": "2026-03-26T10:58:44.926549+00:00",
      "event": "CLAIMED",
      "agent": "Architect",
      "machine_id": "pop-os",
      "from_stage": "READY",
      "to_stage": "READY",
      "details": "Claimed by reaperoak@pop-os via Architect, lease until 2026-03-26T11:28:44.926532+00:00"
    },
    {
      "timestamp": "2026-03-26T11:01:49.774556+00:00",
      "event": "STAGE_COMPLETED",
      "agent": "Architect",
      "machine_id": "system",
      "from_stage": "READY",
      "to_stage": "ARCHITECT",
      "details": "Advanced from READY to ARCHITECT"
    },
    {
      "timestamp": "2026-03-26T11:01:49.807398+00:00",
      "event": "STAGE_COMPLETED",
      "agent": "Architect",
      "machine_id": "system",
      "from_stage": "ARCHITECT",
      "to_stage": "DOCS",
      "details": "Advanced from ARCHITECT to DOCS"
    },
    {
      "timestamp": "2026-03-26T11:01:49.842881+00:00",
      "event": "STAGE_COMPLETED",
      "agent": "Architect",
      "machine_id": "system",
      "from_stage": "DOCS",
      "to_stage": "VALIDATION",
      "details": "Advanced from DOCS to VALIDATION"
    },
    {
      "timestamp": "2026-03-26T11:01:49.892473+00:00",
      "event": "STAGE_COMPLETED",
      "agent": "Architect",
      "machine_id": "system",
      "from_stage": "VALIDATION",
      "to_stage": "DONE",
      "details": "Advanced from VALIDATION to DONE"
    }
  ],
  "source_task_file": "TODO/tasks/EP3-skills-standard.md",
  "tags": [
    "skills-standard",
    "agentskills-io",
    "EP3"
  ]
}
